src/__init__.py
src/config_parser.py
src/cron_job_scheduler.py
src/main.py
src/ml_models_lib/__init__.py
src/ml_models_lib/lsw_kisters_access.py
kistersPREP-0.0.1.dist-info/METADATA
kistersPREP-0.0.1.dist-info/WHEEL
kistersPREP-0.0.1.dist-info/top_level.txt
kistersPREP-0.0.1.dist-info/RECORD
