Metadata-Version: 2.1
Name: kistersPREP
Version: 0.0.1
Summary: Library for LSW Kisters PREP access
Home-page: UNKNOWN
Author: Shyne Sukumaran
License: LSW
Platform: UNKNOWN
